COPYING.txt
MANIFEST.in
README.txt
setup.py
m79commons/__init__.py
m79commons/commons.py
m79commons/m79commons.py
m79commons.egg-info/PKG-INFO
m79commons.egg-info/SOURCES.txt
m79commons.egg-info/dependency_links.txt
m79commons.egg-info/top_level.txt