Metadata-Version: 1.1
Name: m79commons
Version: 1.2.4
Summary: minus79's commons lib
Home-page: https://github.com/youraccount/foolib
Author: Minus Seventynine
Author-email: gergely06@gmail.com
License: UNKNOWN
Platform: UNKNOWN
Classifier: Programming Language :: Python
Classifier: Programming Language :: Python :: 2
Classifier: License :: OSI Approved :: GNU General Public License (GPL)
Classifier: Operating System :: OS Independent
Classifier: Development Status :: 1 - Planning
Classifier: Environment :: Console
Classifier: Intended Audience :: Science/Research
Classifier: Topic :: Scientific/Engineering :: GIS
